[{"id":"1545012203-1-1","algorithm-id":"1545012203","order-id":1,"order-event-id":1,"symbol":"UDOW.YahooData 2S","time":1282276800.0,"status":"submitted","fill-price":0.0,"fill-price-currency":"USD","fill-quantity":0.0,"direction":"buy","is-assignment":false,"quantity":5739.0,"limit-price":3.48},{"id":"1545012203-1-2","algorithm-id":"1545012203","order-id":1,"order-event-id":2,"symbol":"UDOW.YahooData 2S","time":1282363200.0,"status":"filled","order-fee-amount":0.0,"order-fee-currency":"USD","fill-price":3.430833101272583,"fill-price-currency":"USD","fill-quantity":5739.0,"direction":"buy","is-assignment":false,"quantity":5739.0,"limit-price":3.48},{"id":"1545012203-2-1","algorithm-id":"1545012203","order-id":2,"order-event-id":1,"symbol":"UDOW.YahooData 2S","time":1288324800.0,"status":"submitted","fill-price":0.0,"fill-price-currency":"USD","fill-quantity":0.0,"direction":"buy","is-assignment":false,"quantity":3659.0,"limit-price":4.39},{"id":"1545012203-3-1","algorithm-id":"1545012203","order-id":3,"order-event-id":1,"symbol":"UDOW.YahooData 2S","time":1288670400.0,"status":"submitted","fill-price":0.0,"fill-price-currency":"USD","fill-quantity":0.0,"direction":"buy","is-assignment":false,"quantity":3642.0,"limit-price":4.41},{"id":"1545012203-2-2","algorithm-id":"1545012203","order-id":2,"order-event-id":2,"symbol":"UDOW.YahooData 2S","time":1289970000.0,"status":"filled","order-fee-amount":0.0,"order-fee-currency":"USD","fill-price":4.3045830726623535,"fill-price-currency":"USD","fill-quantity":3659.0,"direction":"buy","is-assignment":false,"quantity":3659.0,"limit-price":4.39},{"id":"1545012203-3-2","algorithm-id":"1545012203","order-id":3,"order-event-id":2,"symbol":"UDOW.YahooData 2S","time":1289970000.0,"status":"filled","order-fee-amount":0.0,"order-fee-currency":"USD","fill-price":4.3045830726623535,"fill-price-currency":"USD","fill-quantity":3642.0,"direction":"buy","is-assignment":false,"quantity":3642.0,"limit-price":4.41},{"id":"1545012203-4-1","algorithm-id":"1545012203","order-id":4,"order-event-id":1,"symbol":"UDOW.YahooData 2S","time":1296277200.0,"status":"submitted","fill-price":0.0,"fill-price-currency":"USD","fill-quantity":0.0,"direction":"buy","is-assignment":false,"quantity":1832.0,"limit-price":5.34},{"id":"1545012203-5-1","algorithm-id":"1545012203","order-id":5,"order-event-id":1,"symbol":"UDOW.YahooData 2S","time":1298437200.0,"status":"submitted","fill-price":0.0,"fill-price-currency":"USD","fill-quantity":0.0,"direction":"buy","is-assignment":false,"quantity":1656.0,"limit-price":5.9},{"id":"1545012203-5-2","algorithm-id":"1545012203","order-id":5,"order-event-id":2,"symbol":"UDOW.YahooData 2S","time":1298523600.0,"status":"filled","order-fee-amount":0.0,"order-fee-currency":"USD","fill-price":5.759582996368408,"fill-price-currency":"USD","fill-quantity":1656.0,"direction":"buy","is-assignment":false,"quantity":1656.0,"limit-price":5.9},{"id":"1545012203-4-2","algorithm-id":"1545012203","order-id":4,"order-event-id":2,"symbol":"UDOW.YahooData 2S","time":1300334400.0,"status":"filled","order-fee-amount":0.0,"order-fee-currency":"USD","fill-price":5.0704169273376465,"fill-price-currency":"USD","fill-quantity":1832.0,"direction":"buy","is-assignment":false,"quantity":1832.0,"limit-price":5.34},{"id":"1545012203-6-1","algorithm-id":"1545012203","order-id":6,"order-event-id":1,"symbol":"UDOW.YahooData 2S","time":1300334400.0,"status":"submitted","fill-price":0.0,"fill-price-currency":"USD","fill-quantity":0.0,"direction":"buy","is-assignment":false,"quantity":1185.0,"limit-price":5.07},{"id":"1545012203-7-1","algorithm-id":"1545012203","order-id":7,"order-event-id":1,"symbol":"UDOW.YahooData 2S","time":1303185600.0,"status":"submitted","fill-price":0.0,"fill-price-currency":"USD","fill-quantity":0.0,"direction":"buy","is-assignment":false,"quantity":1024.0,"limit-price":5.87}]